{
  "name": "mblwhoilibrary_drupal_app",
  "description": "Installs/Configures test_dla_drupal_app",
  "long_description": "= DESCRIPTION:\n\nThis cookbook sets up the www.mblwhoilibrary.org drupal website.\n\n= REQUIREMENTS:\n\n* mblwhoilibrary_web_env cookbook\n\n= ATTRIBUTES:\n\n= USAGE:\n\n",
  "maintainer": "YOUR_COMPANY_NAME",
  "maintainer_email": "YOUR_EMAIL",
  "license": "All rights reserved",
  "platforms": {
  },
  "dependencies": {
    "mblwhoilibrary_web_env": [

    ]
  },
  "recommendations": {
  },
  "suggestions": {
  },
  "conflicting": {
  },
  "providing": {
  },
  "replacing": {
  },
  "attributes": {
  },
  "groupings": {
  },
  "recipes": {
  },
  "version": "0.0.1"
}